Metadata-Version: 2.1
Name: odoo12-addon-l10n-br-delivery
Version: 12.0.3.1.0
Summary: This module changes the delivery model strategy to match brazilian standards.
Home-page: https://github.com/OCA/l10n-brazil
Author: Akretion, Odoo Community Association (OCA)
Author-email: support@odoo-community.org
License: AGPL-3
Platform: UNKNOWN
Classifier: Programming Language :: Python
Classifier: Framework :: Odoo
Classifier: Framework :: Odoo :: 12.0
Classifier: License :: OSI Approved :: GNU Affero General Public License v3
Requires-Python: >=3.5
Requires-Dist: odoo12-addon-delivery-carrier-partner
Requires-Dist: odoo12-addon-l10n-br-sale-stock
Requires-Dist: odoo (<12.1dev,>=12.0a)
